statok/statok.py
statok-1.0.0.dist-info/METADATA
statok-1.0.0.dist-info/WHEEL
statok-1.0.0.dist-info/top_level.txt
statok-1.0.0.dist-info/RECORD
