Metadata-Version: 2.1
Name: statok
Version: 1.0.0
Summary: A simple module to get statistics of a tiktok account
Home-page: https://github.com/ProgrammingMyLife/statstok
Author: Classified
Author-email: futuredd10@gmail.com
License: UNKNOWN
Platform: UNKNOWN
Requires-Dist: bs4
Requires-Dist: requests
